LEMBAS/__init__.py
LEMBAS/io.py
LEMBAS/plotting.py
LEMBAS/utilities.py
LEMBAS/model/__init__.py
LEMBAS/model/activation_functions.py
LEMBAS/model/bionetwork.py
LEMBAS/model/model_utilities.py
LEMBAS/model/train.py
LEMBAS_re-0.1.0.dist-info/LICENSE.txt
LEMBAS_re-0.1.0.dist-info/METADATA
LEMBAS_re-0.1.0.dist-info/WHEEL
LEMBAS_re-0.1.0.dist-info/top_level.txt
LEMBAS_re-0.1.0.dist-info/RECORD
