Metadata-Version: 2.1
Name: LEMBAS_re
Version: 0.1.0
Summary: Re-implementation of LEMBAS (https://github.com/Lauffenburger-Lab/LEMBAS)
Home-page: https://github.com/hmbaghdassarian/LEMBAS
Author: Hratch Baghdassarian
Author-email: hmbaghdassarian@gmail.com
License: MIT
Project-URL: Documentation, https://hmbaghdassarian.github.io/LEMBAS/
Classifier: License :: OSI Approved :: MIT License
Classifier: Programming Language :: Python :: 3
Classifier: Topic :: Software Development :: Libraries
Classifier: Topic :: Scientific/Engineering
Classifier: Topic :: Scientific/Engineering :: Bio-Informatics
Classifier: Operating System :: Microsoft :: Windows
Classifier: Operating System :: Unix
Classifier: Operating System :: POSIX
Classifier: Operating System :: MacOS :: MacOS X
License-File: LICENSE.txt
Requires-Dist: pandas
Requires-Dist: scikit-learn
Requires-Dist: plotnine
Requires-Dist: leidenalg
Requires-Dist: torch >=2.1.0
Requires-Dist: annotated-types
Provides-Extra: interactive
Requires-Dist: jupyter ; extra == 'interactive'
Requires-Dist: ipykerne ; extra == 'interactive'
